figo/__init__.py
figo/credentials.py
figo/figo.py
figo/models.py
figo/version.py
python_figo-3.1.0.dist-info/AUTHORS
python_figo-3.1.0.dist-info/METADATA
python_figo-3.1.0.dist-info/WHEEL
python_figo-3.1.0.dist-info/pbr.json
python_figo-3.1.0.dist-info/top_level.txt
python_figo-3.1.0.dist-info/RECORD
