Metadata-Version: 2.1
Name: python-figo
Version: 3.1.0
Summary: Python bindings for the figo Connect API: http://docs.figo.io
Home-page: https://www.figo.io
Author: figo GmbH
Author-email: devs@figo.io
License: BSD License
Platform: UNKNOWN
Classifier: License :: OSI Approved :: BSD License
Classifier: Operating System :: OS Independent
Classifier: Programming Language :: Python
Classifier: Programming Language :: Python :: 2
Classifier: Programming Language :: Python :: 2.7
Classifier: Programming Language :: Python :: 3
Classifier: Programming Language :: Python :: 3.5
Classifier: Programming Language :: Python :: 3.6
Classifier: Development Status :: 5 - Production/Stable
Classifier: Intended Audience :: Developers
Classifier: Topic :: Office/Business :: Financial
Classifier: Topic :: Internet
Requires-Dist: python-dateutil
Requires-Dist: requests
Requires-Dist: requests-toolbelt
Requires-Dist: setuptools-scm
Provides-Extra: webdemo
Requires-Dist: Flask ; extra == 'webdemo'
Requires-Dist: flask-bootstrap ; extra == 'webdemo'
Requires-Dist: Jinja2 ; extra == 'webdemo'
